{
	"_description": "Configuration file for uncertainties evaluation in PROCESS",
	"_author": "Hanni Lux",
	
	"config": {
		  "runtitle": "testrun for uncertainty tool",
		  "IN.DAT_path": "IN.DAT_demo2",
		  "process_bin": "~pknight/process/branches/master/process.exe",
		  "working_directory": "Run1",
		  "pseudorandom_seed": 2
		  },
	"uncertainties": [
		{
               	"Varname":"flhthresh",
               	"Errortype":"Gaussian",
               	"Mean":1.0,
               	"Std":0.05
          	},          
          	{
               	"Varname":"rcore",
               	"Errortype":"Uniform",
               	"Lowerbound":0.6,
               	"Upperbound":0.9
          	},
          	{
               	"Varname":"Hfact",
               	"Errortype":"Relative",
               	"Mean":1.0,
               	"Percentage":10.0
          	} 
	     	],
     "output_vars": [ "rmajor", "dene", "te", "bt"],
     "no_samples": 1000     
}